argParseFromDoc/AutoArgumentParser.py
argParseFromDoc/__init__.py
argParseFromDoc/autoArgparseFunction.py
argParseFromDoc/commandStrGenerator.py
argParseFromDoc/functionWrapper.py
argParseFromDoc/helpers.py
argparsefromdoc-0.1.6.dist-info/licenses/LICENSE
examples/__init__.py
examples/exampleAdd.py
examples/exampleAdd_previousParser.py
examples/exampleBool.py
examples/exampleClass.py
examples/exampleEasy.py
examples/exampleFromFile.py
examples/exampleIgnore.py
examples/exampleListArg.py
examples/exampleLiteral.py
examples/exampleOptionalArgDefault2.py
examples/exampleOptionalArgDefault_withOptional.py
examples/exampleOptionalLiteral.py
tests/__init__.py
tests/test_argParseCommandGenerator.py
tests/test_argParseFromDoc.py
argparsefromdoc-0.1.6.dist-info/METADATA
argparsefromdoc-0.1.6.dist-info/WHEEL
argparsefromdoc-0.1.6.dist-info/top_level.txt
argparsefromdoc-0.1.6.dist-info/RECORD
