Metadata-Version: 2.4
Name: argParseFromDoc
Version: 0.1.6
Summary: Simple argument parser for documented functions
Home-page: https://github.com/rsanchezgarc/argParseFromDoc
Author: Ruben Sanchez-Garcia
Author-email: ruben.sanchez-garcia@stats.ox.ac.uk
License: Apache 2.0
Keywords: argument parser ArgParser docstring argparse
License-File: LICENSE
Requires-Dist: docstring-parser>=0.12
Dynamic: author
Dynamic: author-email
Dynamic: description
Dynamic: description-content-type
Dynamic: home-page
Dynamic: keywords
Dynamic: license
Dynamic: license-file
Dynamic: requires-dist
Dynamic: summary
